abhedya/__init__.py
abhedya-1.0.40.dist-info/METADATA
abhedya-1.0.40.dist-info/WHEEL
abhedya-1.0.40.dist-info/top_level.txt
abhedya-1.0.40.dist-info/RECORD
