Metadata-Version: 2.4
Name: abhedya
Version: 1.0.40
Summary: Sanskrit-Encoded Post-Quantum Cryptography SDK
Author-email: ParamTatva <bot@paramtatva.org>
Project-URL: Homepage, https://github.com/ParamTatva-org/abhedyam
Project-URL: Bug Tracker, https://github.com/ParamTatva-org/abhedyam/issues
Classifier: Programming Language :: Python :: 3
Classifier: License :: OSI Approved :: MIT License
Classifier: Operating System :: OS Independent
Requires-Python: >=3.7
